{
  "TableNo": "99000758",
  "TableName": "Machine Center",
  "Name": "Prod. Order Need (Qty.)",
  "SumFieldTable": "Prod. Order Capacity Need",
  "SumFieldName": "Allocated Time",
  "Type": "SumField",
  "Filters": [
    {
      "Field": "Type",
      "Type": "Static",
      "Value": "\"Machine Center\""
    },
    {
      "Field": "No.",
      "Type": "Static"
    },
    {
      "Field": "Status",
      "Type": "Static"
    },
    {
      "Field": "Date",
      "Type": "Column Period"
    },
    {
      "Field": "Requested Only",
      "Type": "Static",
      "Value": "false"
    }
  ]
}